setup.py
python_voicetext.egg-info/PKG-INFO
python_voicetext.egg-info/SOURCES.txt
python_voicetext.egg-info/dependency_links.txt
python_voicetext.egg-info/requires.txt
python_voicetext.egg-info/top_level.txt
test/test_voicetext.py
voicetext/__init__.py