Metadata-Version: 1.1
Name: python-voicetext
Version: 0.2.1
Summary: Voice synthesiser using VoiceText Web API
Home-page: https://github.com/youtalk/python-voicetext
Author: Yutaka Kondo
Author-email: yutaka.kondo@youtalk.jp
License: Apache License 2.0
Download-URL: https://github.com/youtalk/python-voicetext/releases/tag/0.2.1
Platform: POSIX
Platform: Mac OS X
Platform: Windows
Classifier: Environment :: Console
Classifier: Intended Audience :: Developers
Classifier: License :: OSI Approved :: Apache Software License
Classifier: Operating System :: OS Independent
Classifier: Programming Language :: Python
Classifier: Topic :: Multimedia :: Sound/Audio
